AUTHORS.rst
CONTRIBUTING.rst
HISTORY.rst
LICENSE
MANIFEST.in
README.rst
setup.cfg
setup.py
etcaetera/__init__.py
etcaetera/config.py
etcaetera/constants.py
etcaetera/exceptions.py
etcaetera/formatters.py
etcaetera/utils.py
etcaetera.egg-info/PKG-INFO
etcaetera.egg-info/SOURCES.txt
etcaetera.egg-info/dependency_links.txt
etcaetera.egg-info/not-zip-safe
etcaetera.egg-info/requires.txt
etcaetera.egg-info/top_level.txt
etcaetera/adapter/__init__.py
etcaetera/adapter/base.py
etcaetera/adapter/defaults.py
etcaetera/adapter/env.py
etcaetera/adapter/file.py
etcaetera/adapter/module.py
etcaetera/adapter/overrides.py
etcaetera/adapter/set.py