Metadata-Version: 1.1
Name: etcaetera
Version: 0.4.3
Summary: Manage multiple configuration sources in a single place
Home-page: https://github.com/oleiade/etcaetera
Author: Oleiade
Author-email: tcrevon@gmail.com
License: MIT
Keywords: etcaetera
Platform: UNKNOWN
Classifier: Development Status :: 2 - Pre-Alpha
Classifier: Intended Audience :: Developers
Classifier: License :: OSI Approved :: MIT License
Classifier: Natural Language :: English
Classifier: Programming Language :: Python :: 2
Classifier: Programming Language :: Python :: 2.7
Classifier: Programming Language :: Python :: 3
Classifier: Programming Language :: Python :: 3.3
